skipole/__init__.py
skipole/__main__.py
skipole/skis.py
skipole/textblocks.py
skipole/ski/__init__.py
skipole/ski/dump_project.py
skipole/ski/excepts.py
skipole/ski/folder_class_definition.py
skipole/ski/page_class_definition.py
skipole/ski/project_class_definition.py
skipole/ski/read_json.py
skipole/ski/skiboot.py
skipole/ski/tag.py
skipole/ski/responders/__init__.py
skipole/ski/responders/checkers.py
skipole/ski/responders/navigators.py
skipole/ski/responders/submitters.py
skipole/ski/validators/__init__.py
skipole/ski/validators/basic.py
skipole/ski/validators/paths.py
skipole/ski/widgets/__init__.py
skipole/ski/widgets/checkbox.py
skipole/ski/widgets/confirm.py
skipole/ski/widgets/debug_tools.py
skipole/ski/widgets/dropdown.py
skipole/ski/widgets/error_messages.py
skipole/ski/widgets/footers.py
skipole/ski/widgets/headers.py
skipole/ski/widgets/info.py
skipole/ski/widgets/inputforms.py
skipole/ski/widgets/inputtables.py
skipole/ski/widgets/inputtext.py
skipole/ski/widgets/links.py
skipole/ski/widgets/lists.py
skipole/ski/widgets/logins.py
skipole/ski/widgets/paras.py
skipole/ski/widgets/radio.py
skipole/ski/widgets/svgbasics.py
skipole/ski/widgets/svggraphs.py
skipole/ski/widgets/svgmeters.py
skipole/ski/widgets/tables.py
skipole/ski/widgets/textarea.py
skipole/ski/widgets/upload.py
skipole/skis/data/defaults.json
skipole/skis/data/project.json
skipole/skis/data/textblocks_json/en.json
skipole/skis/static/css/theme1.css
skipole/skis/static/css/theme2.css
skipole/skis/static/css/theme3.css
skipole/skis/static/css/theme4.css
skipole/skis/static/css/w3.css
skipole/skis/static/js/basic.js
skipole/skis/static/js/checkbox.js
skipole/skis/static/js/confirm.js
skipole/skis/static/js/debug_tools.js
skipole/skis/static/js/dropdown.js
skipole/skis/static/js/error_messages.js
skipole/skis/static/js/footers.js
skipole/skis/static/js/headers.js
skipole/skis/static/js/info.js
skipole/skis/static/js/inputforms.js
skipole/skis/static/js/inputtables.js
skipole-5.6.1.dist-info/LICENSE
skipole-5.6.1.dist-info/WHEEL
skipole-5.6.1.dist-info/METADATA
skipole-5.6.1.dist-info/RECORD
