Metadata-Version: 2.1
Name: skipole
Version: 5.6.1
Summary: A WSGI Application generator
Keywords: wsgi,application,web,framework
Author-email: Bernard Czenkusz <bernie@skipole.co.uk>
Requires-Python: >=3.8
Classifier: License :: OSI Approved :: MIT License
Classifier: Operating System :: OS Independent
Classifier: Topic :: Internet :: WWW/HTTP :: WSGI :: Application
Project-URL: Documentation, https://bernie-skipole.github.io/skipole/
Project-URL: Source, https://github.com/bernie-skipole/skipole
